xdatool/__init__.py
xdatool/cli.py
xdatool-0.1.0.dist-info/METADATA
xdatool-0.1.0.dist-info/WHEEL
xdatool-0.1.0.dist-info/entry_points.txt
xdatool-0.1.0.dist-info/top_level.txt
xdatool-0.1.0.dist-info/RECORD
